edcba/__init__.py
edcba-0.0.1.dist-info/METADATA
edcba-0.0.1.dist-info/WHEEL
edcba-0.0.1.dist-info/top_level.txt
edcba-0.0.1.dist-info/RECORD
