Metadata-Version: 2.4
Name: edcba
Version: 0.0.1
Summary: EDCBA
Author: Your Name
Author-email: your.email@example.com
Classifier: Development Status :: 1 - Planning
Classifier: Programming Language :: Python :: 3
Requires-Python: >=3.6
Dynamic: author
Dynamic: author-email
Dynamic: classifier
Dynamic: description
Dynamic: description-content-type
Dynamic: requires-python
Dynamic: summary
